query_phenomizer/__init__.py
query_phenomizer/__main__.py
query_phenomizer/cli.py
query_phenomizer/log.py
query_phenomizer/utils.py
query_phenomizer-1.2.1.dist-info/LICENSE
query_phenomizer-1.2.1.dist-info/METADATA
query_phenomizer-1.2.1.dist-info/WHEEL
query_phenomizer-1.2.1.dist-info/entry_points.txt
query_phenomizer-1.2.1.dist-info/top_level.txt
query_phenomizer-1.2.1.dist-info/RECORD
