Metadata-Version: 2.1
Name: query_phenomizer
Version: 1.2.1
Summary: Tool for query and parsing the phenomizer tool
Home-page: https://www.github.com/moonso/query_phenomizer
Author: Måns Magnusson
Author-email: mans.magnusson@scilifelab.se
License: Modified BSD
Keywords: hpo development phenomizer
Classifier: Development Status :: 3 - Alpha
Classifier: Intended Audience :: Developers
Classifier: Topic :: Software Development
Classifier: License :: OSI Approved :: MIT License
Classifier: Programming Language :: Python :: 2
Classifier: Programming Language :: Python :: 2.7
Classifier: Programming Language :: Python :: 3
Classifier: Programming Language :: Python :: 3.3
Classifier: Programming Language :: Python :: 3.4
Classifier: Environment :: Console
License-File: LICENSE
Requires-Dist: click
Requires-Dist: requests
Requires-Dist: pytest
